oaios/__init__.py
oaios/asgi.py
oaios/settings.py
oaios/urls.py
oaios/wsgi.py
oaios-0.3.0.dist-info/LICENSE.md
oaios-0.3.0.dist-info/METADATA
oaios-0.3.0.dist-info/WHEEL
oaios-0.3.0.dist-info/top_level.txt
oaios-0.3.0.dist-info/RECORD
